novatel_edie/__init__.py
novatel_edie/__main__.py
novatel_edie/bindings.pyd
novatel_edie/bindings.pyi
novatel_edie/cli.py
novatel_edie/database.json
novatel_edie/enums.py
novatel_edie/enums.pyi
novatel_edie/installer.py
novatel_edie/messages.py
novatel_edie/messages.pyi
novatel_edie/stubgen.py
novatel_edie-2.6.8.dist-info/METADATA
novatel_edie-2.6.8.dist-info/WHEEL
novatel_edie-2.6.8.dist-info/entry_points.txt
novatel_edie-2.6.8.dist-info/licenses/LICENSE
novatel_edie-2.6.8.dist-info/RECORD
