Metadata-Version: 2.2
Name: novatel_edie
Version: 2.6.8
Summary: SDK for interfacing with and decoding data from NovAtel OEM7 receivers
License: MIT
Requires-Python: >=3.8
Requires-Dist: importlib_resources
Requires-Dist: typer>=0.15
